{"is_source_file": false, "format": "", "description": "", "external_files": [], "external_methods": [], "published": [], "classes": [], "methods": [], "calls": [], "search-terms": [], "state": 2, "file_id": 9, "knowledge_revision": 28, "git_revision": "4dada90fc74bf194e2e9c9e3e312a6a316cdb8cd", "hash": "126431474bbc1150a2e3d82ca40e68d3", "format-version": 4, "code-base-name": "subtitle_frontend", "filename": "subtitle_frontend/package.json", "revision_history": [{"28": "4dada90fc74bf194e2e9c9e3e312a6a316cdb8cd"}]}