{"is_source_file": false, "format": null, "description": "", "external_files": [], "external_methods": [], "published": [], "classes": [], "methods": [], "calls": [], "search-terms": ["subtitle", "frontend", "React", "UI", "video", "subtitle upload", "backend"], "state": 2, "file_id": 3, "knowledge_revision": 28, "git_revision": "ae4a08cb32a1ad241bc53d267f724f182a641655", "hash": "bff0400fea695e7d3df07671f9377fa0", "format-version": 4, "code-base-name": "subtitle_frontend", "filename": "subtitle_frontend/README.md", "revision_history": [{"28": "ae4a08cb32a1ad241bc53d267f724f182a641655"}]}